veris_cli/__init__.py
veris_cli/api.py
veris_cli/cli.py
veris_cli/config.py
veris_cli/errors.py
veris_cli/fs.py
veris_cli/loaders.py
veris_cli/results.py
veris_cli/run_models.py
veris_cli/runs.py
veris_cli/types.py
veris_cli/commands/__init__.py
veris_cli/commands/agent.py
veris_cli/commands/init.py
veris_cli/commands/scenario.py
veris_cli/commands/setup_local.py
veris_cli/commands/simulation.py
veris_cli/models/CLAUDE.md
veris_cli/models/README.md
veris_cli/models/agent_config.py
veris_cli/models/api.py
veris_cli/models/config.py
veris_cli/models/engine.py
veris_cli/models/evals/__init__.py
veris_cli/models/evals/api.py
veris_cli/models/evals/evaluation.py
veris_cli/models/evals/summary.py
veris_cli/models/scenarios/CLAUDE.md
veris_cli/models/scenarios/README.md
veris_cli/models/scenarios/__init__.py
veris_cli/models/scenarios/agent_spec.py
veris_cli/models/scenarios/config.py
veris_cli/models/scenarios/generation.py
veris_cli/models/scenarios/scenario.py
veris_cli-1.14.0.dist-info/METADATA
veris_cli-1.14.0.dist-info/WHEEL
veris_cli-1.14.0.dist-info/entry_points.txt
veris_cli-1.14.0.dist-info/RECORD
