Metadata-Version: 2.4
Name: veris-cli
Version: 1.14.0
Summary: CLI to connect local agents to the Veris backend
Project-URL: Homepage, https://github.com/veris-ai/veris-cli
Project-URL: Bug Tracker, https://github.com/veris-ai/veris-cli/issues
Author: Veris
Requires-Python: >=3.11
Requires-Dist: httpx>=0.27
Requires-Dist: jinja2>=3.1.6
Requires-Dist: pre-commit>=4.3.0
Requires-Dist: pydantic>=2.7
Requires-Dist: pyngrok>=7.4.0
Requires-Dist: python-dotenv>=1.1.1
Requires-Dist: pyyaml>=6.0.1
Requires-Dist: rich>=13.7
Requires-Dist: tomli-w>=1.0.0
Requires-Dist: typer>=0.12
Provides-Extra: dev
Requires-Dist: pre-commit>=3.7.0; extra == 'dev'
Provides-Extra: test
Requires-Dist: pytest-asyncio>=0.23.0; extra == 'test'
Requires-Dist: pytest-cov>=4.1.0; extra == 'test'
Requires-Dist: pytest>=8.2; extra == 'test'
